CHANGES.txt
COPYRIGHT.txt
LICENSE.txt
MULTI_PLATFORM_TESTS.txt
README.txt
bootstrap.py
buildout.cfg
setup.py
docs/source/conf.py
docs/source/index.rst
src/ulif/__init__.py
src/ulif.loghandlers.egg-info/PKG-INFO
src/ulif.loghandlers.egg-info/SOURCES.txt
src/ulif.loghandlers.egg-info/dependency_links.txt
src/ulif.loghandlers.egg-info/entry_points.txt
src/ulif.loghandlers.egg-info/namespace_packages.txt
src/ulif.loghandlers.egg-info/not-zip-safe
src/ulif.loghandlers.egg-info/requires.txt
src/ulif.loghandlers.egg-info/top_level.txt
src/ulif/loghandlers/TODO.txt
src/ulif/loghandlers/__init__.py
src/ulif/loghandlers/handlers.py
src/ulif/loghandlers/test_handlers.py