Metadata-Version: 1.0
Name: ulif.loghandlers
Version: 0.1.1
Summary: Additional logging handlers.
Home-page: http://pypi.python.org/pypi/ulif.loghandlers
Author: Uli Fouquet
Author-email: uli@gnufix.de
License: LGPL
Keywords: logging logger rotating
Platform: UNKNOWN
Classifier: Development Status :: 3 - Alpha
Classifier: Framework :: Buildout
Classifier: Intended Audience :: Developers
Classifier: Intended Audience :: System Administrators
Classifier: License :: OSI Approved :: GNU Lesser General Public License v3 or later (LGPLv3+)
Classifier: Programming Language :: Python
Classifier: Operating System :: OS Independent
Classifier: Topic :: Software Development :: Libraries :: Python Modules
Classifier: Topic :: System :: Logging
Classifier: Programming Language :: Python :: 2.6
Classifier: Programming Language :: Python :: 2.7
